{"227":{"name":"Evren","mah":[{"id":"4458","name":"Eskitorunobasi Mah","pk":"6770"},{"id":"4459","name":"Esentepe Mah","pk":"6770"},{"id":"4460","name":"Cebirli Mah","pk":"6770"},{"id":"4461","name":"İbrahimbeyli Mah","pk":"6770"},{"id":"4462","name":"Modern Mah","pk":"6770"},{"id":"4463","name":"Solakuşaği Mah","pk":"6770"},{"id":"4464","name":"Şerafettin Yilmaz Mah","pk":"6770"},{"id":"4465","name":"İnebeyli Mah","pk":"6770"},{"id":"4466","name":"Demirayak Mah","pk":"6770"},{"id":"4467","name":"Yeni Mah","pk":"6770"},{"id":"4468","name":"Yusufuşaği Mah","pk":"6770"},{"id":"4469","name":"Altinbaşak Mah","pk":"6770"},{"id":"4470","name":"Çatalpinar Mah","pk":"6770"}]}}