{"973":{"name":"Çerkezköy","mah":[{"id":"19646","name":"Veliköy-Yaliboyu Osb Mah","pk":"59500"},{"id":"19647","name":"Yildirim Beyazit Mah","pk":"59500"},{"id":"19648","name":"Bağlik Mah","pk":"59500"},{"id":"19649","name":"Gazi Osman Paşa Mah","pk":"59500"},{"id":"19650","name":"Fatih Mah","pk":"59500"},{"id":"19651","name":"Gazi Mustafa Kemal Paşa Osb Mah","pk":"59500"},{"id":"19652","name":"Veliköy Osb Mah","pk":"59500"},{"id":"19653","name":"Cumhuriyet Mah","pk":"59500"},{"id":"19654","name":"Fevzi Paşa Mah","pk":"59500"},{"id":"19655","name":"Yildirim Beyazit Osb Mah","pk":"59500"},{"id":"19656","name":"Gazi Mustafa Kemalpaşa Mah","pk":"59500"},{"id":"19657","name":"Gazi Osman Paşa Osb Mah","pk":"59500"},{"id":"19658","name":"Veliköy Mah","pk":"59500"},{"id":"19659","name":"İstasyon Mah","pk":"59500"},{"id":"19660","name":"Kizilpinar Mah","pk":"59500"}]}}