{"68":{"name":"Güneysinir","mah":[{"id":"1472","name":"Durayda Mah","pk":"42490"},{"id":"1473","name":"Aydoğmuş Mah","pk":"42490"},{"id":"1474","name":"Avcitepe Mah","pk":"42490"},{"id":"1475","name":"Kizilöz Mah","pk":"42490"},{"id":"1476","name":"Gürağaç Mah","pk":"42490"},{"id":"1477","name":"Bardas Mah","pk":"42490"},{"id":"1478","name":"Mehmet Ali Mah","pk":"42490"},{"id":"1479","name":"Örenboyali Mah","pk":"42490"},{"id":"1480","name":"Kayaağzi Mah","pk":"42490"},{"id":"1481","name":"Ömeroğlu Mah","pk":"42490"},{"id":"1482","name":"Kurukavak Mah","pk":"42490"},{"id":"1483","name":"Habiller Mah","pk":"42490"},{"id":"1484","name":"Emirhan Mah","pk":"42490"},{"id":"1485","name":"Mevlana Mah","pk":"42490"},{"id":"1486","name":"Güneybağ Mah","pk":"42490"},{"id":"1487","name":"Karasinir Mah","pk":"42490"},{"id":"1488","name":"Karagüney Mah","pk":"42490"},{"id":"1489","name":"Sarihaci Mah","pk":"42490"}]}}