{"1581":{"name":"Gerede","mah":[{"id":"39639","name":"Demirciler Mah","pk":"14900"},{"id":"39640","name":"Dayioğlu Mah","pk":"14900"},{"id":"39641","name":"Orta Mah","pk":"14900"},{"id":"39642","name":"Seviller Mah","pk":"14900"},{"id":"39643","name":"Kabiller Mah","pk":"14900"},{"id":"39644","name":"Yeni Mah","pk":"14900"},{"id":"39645","name":"Bahçelievler Mah","pk":"14900"},{"id":"39646","name":"Demircilerosb Mah","pk":"14900"},{"id":"39647","name":"Kitirler Mah","pk":"14900"}]},"1582":{"name":"Merkezköyler","mah":[{"id":"39648","name":"Yayla Mah (Bahçedere Köyü)","pk":"14902"},{"id":"39649","name":"Afatlar Yayla Mah (Yaziköy Köyü)","pk":"14902"},{"id":"39650","name":"Orta Mah (Ibricak Köyü)","pk":"14902"},{"id":"39651","name":"Fadillar Mah (Beşkonak Köyü)","pk":"14902"},{"id":"39652","name":"Apsari Mah (Yeşilvadi Köyü)","pk":"14902"},{"id":"39653","name":"Yayla Mah (Aşağiovacik Köyü)","pk":"14902"},{"id":"39654","name":"Merkez Yayla Mah (Dağkara Köyü)","pk":"14902"},{"id":"39655","name":"Yayla Mah (Mircekiraz Köyü)","pk":"14902"},{"id":"39656","name":"Merkez Mah (Aktaş Köyü)","pk":"14902"},{"id":"39657","name":"Demirci Mah (Külef Köyü)","pk":"14902"},{"id":"39658","name":"Kirbizlar Mah (Yukariörenbaşi Köyü)","pk":"14902"},{"id":"39659","name":"Yayla Mah (Kapakli Köyü)","pk":"14902"},{"id":"39660","name":"Gölcük Mah (Aktaş Köyü)","pk":"14902"},{"id":"39661","name":"Yayla Mah (Yakaboy Köyü)","pk":"14902"},{"id":"39662","name":"Yayla Mah (Yazikara Köyü)","pk":"14902"},{"id":"39663","name":"Merkez Mah (Afşartarakçi Köyü)","pk":"14902"},{"id":"39664","name":"Merkez Mah (Yukariovacik Köyü)","pk":"14902"},{"id":"39665","name":"Yayla Mah (Çayörengüney Köyü)","pk":"14902"},{"id":"39666","name":"Zadatlar Mah (Enseliler Köyü)","pk":"14902"},{"id":"39667","name":"Baltacilar Mah (Örencik Köyü)","pk":"14902"},{"id":"39668","name":"Merkez Mah (Kavacik Köyü)","pk":"14902"},{"id":"39669","name":"Mandiralar Mah (Ağizörengüney Köyü)","pk":"14902"},{"id":"39670","name":"Yayla Mah (Elören Köyü)","pk":"14902"},{"id":"39671","name":"Ekmenler Mah (Bahçedere Köyü)","pk":"14902"},{"id":"39672","name":"Yayla Mah (Yeniyapar Köyü)","pk":"14902"},{"id":"39673","name":"Süller Yaylasi Mah (Süllertoklar Köyü)","pk":"14902"},{"id":"39674","name":"Kadimler Mah (Ortaca Köyü)","pk":"14902"},{"id":"39675","name":"Merkez Yayla Mah (Çalaman Köyü)","pk":"14902"},{"id":"39676","name":"Tepe Mah (Yakakaya Köyü)","pk":"14902"},{"id":"39677","name":"Merkez Mah (Tatlar Köyü)","pk":"14902"},{"id":"39678","name":"Merkez Mah (Samat Köyü)","pk":"14902"},{"id":"39679","name":"Haci Muslar Mah (Demircisopran Köyü)","pk":"14902"},{"id":"39680","name":"Merkez Mah (Enseliler Köyü)","pk":"14902"},{"id":"39681","name":"Kandak Mah (Davutbeyli Köyü)","pk":"14902"},{"id":"39682","name":"Yaman Mah (Çalaman Köyü)","pk":"14902"},{"id":"39683","name":"Merkez Mah (Demircisopran Köyü)","pk":"14902"},{"id":"39684","name":"Üçpinar Mah (Yaziköy Köyü)","pk":"14902"},{"id":"39685","name":"Demirciler  Mah (Merkez Mah) (Güneydemirciler Köyü)","pk":"14902"},{"id":"39686","name":"Markuşa Yaylasi Mah (Göynükören Köyü)","pk":"14902"},{"id":"39687","name":"Merkez Mah (Mircekiraz Köyü)","pk":"14902"},{"id":"39688","name":"Yayla Mah (Dikmen Köyü)","pk":"14902"},{"id":"39689","name":"Deveyataği Yaylasi Mah (Karapazar Köyü)","pk":"14902"},{"id":"39690","name":"Merkez Mah (Aşağiörenbaşi Köyü)","pk":"14902"},{"id":"39691","name":"Merkez Mah (Mangallar Köyü)","pk":"14902"},{"id":"39692","name":"Yukari Mah (Ortaca Köyü)","pk":"14902"},{"id":"39693","name":"Ağagil Mah (Karacadağdemirciler Köyü)","pk":"14902"},{"id":"39694","name":"Emirler Mah (Sungurlar Köyü)","pk":"14902"},{"id":"39695","name":"Yayla Mah (Kayisopran Köyü)","pk":"14902"},{"id":"39696","name":"Mandira Mah (Çukurca Köyü)","pk":"14902"},{"id":"39697","name":"Mehmet Beylik Mah (Havullu Köyü)","pk":"14902"},{"id":"39698","name":"Yayla Mah (Örencik Köyü)","pk":"14902"},{"id":"39699","name":"Yanşaba Yaylasi Mah (Dağkara Köyü)","pk":"14902"},{"id":"39700","name":"Yayla Mah (Sungurlar Köyü)","pk":"14902"},{"id":"39701","name":"Yayla Mah (Mukamlar Köyü)","pk":"14902"},{"id":"39702","name":"Yayla Mah (Afşartarakçi Köyü)","pk":"14902"},{"id":"39703","name":"Toklar Mah (Süllertoklar Köyü)","pk":"14902"},{"id":"39704","name":"Merkez Mah (Kapakli Köyü)","pk":"14902"},{"id":"39705","name":"Yariş Mah (Çoğullu Köyü)","pk":"14902"},{"id":"39706","name":"Yayla Mah (Halaçlar Köyü)","pk":"14902"},{"id":"39707","name":"Ibricak Mah (Ibricak Köyü)","pk":"14902"},{"id":"39708","name":"Yaniklar Mah (Yelkenler Köyü)","pk":"14902"},{"id":"39709","name":"Merkez Yaylasi Mah (Hasanlar Köyü)","pk":"14902"},{"id":"39710","name":"Köy Yaylasi Mah (Bahçedere Köyü)","pk":"14902"},{"id":"39711","name":"Seyitler Yaylasi Mah (Ulaşlar Köyü)","pk":"14902"},{"id":"39712","name":"Yayla Mah (Mürdükler Köyü)","pk":"14902"},{"id":"39713","name":"Merkez Mah (Akçabey Köyü)","pk":"14902"},{"id":"39714","name":"Merkez Mah (Bünüş Köyü)","pk":"14902"},{"id":"39715","name":"Merkez Mah (Kösreli Köyü)","pk":"14902"},{"id":"39716","name":"Merkez Yayla Mah (Ulaşlar Köyü)","pk":"14902"},{"id":"39717","name":"Merkez Yaylasi Mah (Yukariovacik Köyü)","pk":"14902"},{"id":"39718","name":"Aşaği Mah (Balcilar Köyü)","pk":"14902"},{"id":"39719","name":"Yayla Mah (Asmaca Köyü)","pk":"14902"},{"id":"39720","name":"Ispahlar Mah (Sipahiler Köyü)","pk":"14902"},{"id":"39721","name":"Merkez Yayla Mah (Sapanliurgancilar Köyü)","pk":"14902"},{"id":"39722","name":"Dere Mah (Kapakli Köyü)","pk":"14902"},{"id":"39723","name":"Sömerciler Mah (Karacadağdemirciler Köyü)","pk":"14902"},{"id":"39724","name":"Merkez Mah (Çalaman Köyü)","pk":"14902"},{"id":"39725","name":"Seyfe Mah (Külef Köyü)","pk":"14902"},{"id":"39726","name":"Yayla Mah (Karacadağ Köyü)","pk":"14902"},{"id":"39727","name":"Koçlar Mah (Tatlar Köyü)","pk":"14902"},{"id":"39728","name":"Yayla Mah (Aydinlar Köyü)","pk":"14902"},{"id":"39729","name":"Merkez Mah (Yeniyapar Köyü)","pk":"14902"},{"id":"39730","name":"Üçpinar Yayla Mah (Yaziköy Köyü)","pk":"14902"},{"id":"39731","name":"Merkez Mah (Macarlar Köyü)","pk":"14902"},{"id":"39732","name":"Yayla Mah (Akçabey Köyü)","pk":"14902"},{"id":"39733","name":"Yayla Mah (Sipahiler Köyü)","pk":"14902"},{"id":"39734","name":"Merkez Mah (Göynükören Köyü)","pk":"14902"},{"id":"39735","name":"Sinanlar Yayla Mah (Ortaca Köyü)","pk":"14902"},{"id":"39736","name":"Merkez Mah (Zeyneller Köyü)","pk":"14902"},{"id":"39737","name":"Yayla Mah (Demircisopran Köyü)","pk":"14902"},{"id":"39738","name":"Yayla Mah (Akbaş Köyü)","pk":"14902"},{"id":"39739","name":"Merkez Mah (İmamlar Köyü)","pk":"14902"},{"id":"39740","name":"Birinciafşar Köyü","pk":"14902"},{"id":"39741","name":"Ecinlioğlu Mah (Macarlar Köyü)","pk":"14902"},{"id":"39742","name":"Merkez Mah (Bahçedere Köyü)","pk":"14902"},{"id":"39743","name":"Merkez Mah (Yelkenler Köyü)","pk":"14902"},{"id":"39744","name":"Merkez Mah (Çukurca Köyü)","pk":"14902"},{"id":"39745","name":"Merkez Mah (Ulaşlar Köyü)","pk":"14902"},{"id":"39746","name":"Merkez Mah (Kayisopran Köyü)","pk":"14902"},{"id":"39747","name":"Aktaş Mah (Aktaşkurtlar Köyü)","pk":"14902"},{"id":"39748","name":"Kapçi Evi Mah (Çağiş Köyü)","pk":"14902"},{"id":"39749","name":"Çengeller Mah (Muratfakilar Köyü)","pk":"14902"},{"id":"39750","name":"Yayla Mah (Ahmetler Köyü)","pk":"14902"},{"id":"39751","name":"Merkez Mah (Kayikiraz Köyü)","pk":"14902"},{"id":"39752","name":"Hatiplar Mah (Enseliler Köyü)","pk":"14902"},{"id":"39753","name":"Merkez Mah (Akbaş Köyü)","pk":"14902"},{"id":"39754","name":"Sofular Yaylasi Mah (Sofular Köyü)","pk":"14902"},{"id":"39755","name":"Yunuslar Mah (Yakakaya Köyü)","pk":"14902"},{"id":"39756","name":"Seyitler Mah (Ulaşlar Köyü)","pk":"14902"},{"id":"39757","name":"Yayla Mah (Sarioğlu Köyü)","pk":"14902"},{"id":"39758","name":"Kabaklar Mah (Güneydemirciler Köyü)","pk":"14902"},{"id":"39759","name":"Akkadim Yayla Mah (Ortaca Köyü)","pk":"14902"},{"id":"39760","name":"İmreşe Mah (Mangallar Köyü)","pk":"14902"},{"id":"39761","name":"Küllü Yayla Mah (Karapazar Köyü)","pk":"14902"},{"id":"39762","name":"Merkez Mah (Havullu Köyü)","pk":"14902"},{"id":"39763","name":"Merkez Mah (Dursunfaki Köyü)","pk":"14902"},{"id":"39764","name":"Kayabaşi Mah (Karacadağ Köyü)","pk":"14902"},{"id":"39765","name":"Merkez Mah (Ertuğrulköy Köyü)","pk":"14902"},{"id":"39766","name":"Merkez Yaylasi Mah (Havullu Köyü)","pk":"14902"},{"id":"39767","name":"Merkez Yayla Mah (Geçitler Köyü)","pk":"14902"},{"id":"39768","name":"Merkez Mah (Yeşilvadi Köyü)","pk":"14902"},{"id":"39769","name":"Çukur Yayla Mah (Yunuslar Köyü)","pk":"14902"},{"id":"39770","name":"Gökçeler Mah (Bahçedere Köyü)","pk":"14902"},{"id":"39771","name":"Akkadim Mah (Ortaca Köyü)","pk":"14902"},{"id":"39772","name":"Merkez Mah (Eymür Köyü)","pk":"14902"},{"id":"39773","name":"Tataroğlu Mah (Beşkonak Köyü)","pk":"14902"},{"id":"39774","name":"Merkez Yayla Mah (Yaziköy Köyü)","pk":"14902"},{"id":"39775","name":"Afatlar Mah (Yaziköy Köyü)","pk":"14902"},{"id":"39776","name":"Yayla Mah (Yakakaya Köyü)","pk":"14902"},{"id":"39777","name":"Yayla Mah (Kürkçüler Köyü)","pk":"14902"},{"id":"39778","name":"Yayla Mah (Beşkonak Köyü)","pk":"14902"},{"id":"39779","name":"Merkez Mah (Danişmentler Köyü)","pk":"14902"},{"id":"39780","name":"Tozaklar Mah (Karacadağ Köyü)","pk":"14902"},{"id":"39781","name":"Yayla Mah (Ibricak Köyü)","pk":"14902"},{"id":"39782","name":"Yayla Mah (Davutbeyli Köyü)","pk":"14902"},{"id":"39783","name":"Gaziler Mah (Güneydemirciler Köyü)","pk":"14902"},{"id":"39784","name":"Yayla Mah (İmamlar Köyü)","pk":"14902"},{"id":"39785","name":"Gaziler Yayla Mah (Güneydemirciler Köyü)","pk":"14902"},{"id":"39786","name":"Ayvatlar Mah (Göynükören Köyü)","pk":"14902"},{"id":"39787","name":"Merkez Mah (Sungurlar Köyü)","pk":"14902"},{"id":"39788","name":"Yayla Mah (Demirler Köyü)","pk":"14902"},{"id":"39789","name":"Dümenler Mah (Geçitler Köyü)","pk":"14902"},{"id":"39790","name":"Yayla Mah (Enseliler Köyü)","pk":"14902"},{"id":"39791","name":"Merkez Yayla Mah (Ortaca Köyü)","pk":"14902"},{"id":"39792","name":"Merkez Mah (Yağdaş Köyü)","pk":"14902"},{"id":"39793","name":"Haci İpekler Mah (Güneydemirciler Köyü)","pk":"14902"},{"id":"39794","name":"Aşaği Yayla Mah (Göynükören Köyü)","pk":"14902"},{"id":"39795","name":"Merkez Mah (Hacilar Köyü)","pk":"14902"},{"id":"39796","name":"Merkez Mah (Ahmetler Köyü)","pk":"14902"},{"id":"39797","name":"Aşaği Mah (Bünüş Köyü)","pk":"14902"},{"id":"39798","name":"Deyişler Yaylasi Mah (Sofular Köyü)","pk":"14902"},{"id":"39799","name":"Merkez Mah (Mukamlar Köyü)","pk":"14902"},{"id":"39800","name":"Merkez Yayla Mah (Yunuslar Köyü)","pk":"14902"},{"id":"39801","name":"Merkez Mah (Elören Köyü)","pk":"14902"},{"id":"39802","name":"Merkez Mah (Halaçlar Köyü)","pk":"14902"},{"id":"39803","name":"Merkez Mah (Sofular Köyü)","pk":"14902"},{"id":"39804","name":"Yayla Mah (Yukariörenbaşi Köyü)","pk":"14902"},{"id":"39805","name":"Yayla Mah (İkinciafşar Köyü)","pk":"14902"},{"id":"39806","name":"Yayla Mah (Danişmentler Köyü)","pk":"14902"},{"id":"39807","name":"Merkez Mah (Karacadağ Köyü)","pk":"14902"},{"id":"39808","name":"Merkez Mah (Demirler Köyü)","pk":"14902"},{"id":"39809","name":"Yayla Mah (Macarlar Köyü)","pk":"14902"},{"id":"39810","name":"Çukurca Yaylasi Mah (Kösreli Köyü)","pk":"14902"},{"id":"39811","name":"Merkez Mah (Çayören Köyü)","pk":"14902"},{"id":"39812","name":"Çukur Mah (Yunuslar Köyü)","pk":"14902"},{"id":"39813","name":"Demirci Mah (Yukariörenbaşi Köyü)","pk":"14902"},{"id":"39814","name":"Merkez Mah (Kürkçüler Köyü)","pk":"14902"},{"id":"39815","name":"Battallar Mah (Aydinlar Köyü)","pk":"14902"},{"id":"39816","name":"Yayla Mah (Kazanlar Köyü)","pk":"14902"},{"id":"39817","name":"Çağiş Mah (Çağiş Köyü)","pk":"14902"},{"id":"39818","name":"Merkez Mah (Karacadağdemirciler Köyü)","pk":"14902"},{"id":"39819","name":"Yayla Mah (Yağdaş Köyü)","pk":"14902"},{"id":"39820","name":"Merkez Mah (Sarioğlu Köyü)","pk":"14902"},{"id":"39821","name":"Yayla Mah (İnköy Köyü)","pk":"14902"},{"id":"39822","name":"Kurtlar Mah (Aktaşkurtlar Köyü)","pk":"14902"},{"id":"39823","name":"Sağlik Mah (Halaçlar Köyü)","pk":"14902"},{"id":"39824","name":"Yayla Mah (Külef Köyü)","pk":"14902"},{"id":"39825","name":"Merkez Mah (Kalaç Köyü)","pk":"14902"},{"id":"39826","name":"Yeni Mah (Ibricak Köyü)","pk":"14902"},{"id":"39827","name":"Deyişler Mah (Sofular Köyü)","pk":"14902"},{"id":"39828","name":"Karakuz Mah (Ertuğrulköy Köyü)","pk":"14902"},{"id":"39829","name":"Işikli Mah (Ulaşlar Köyü)","pk":"14902"},{"id":"39830","name":"Merkez Mah (İnköy Köyü)","pk":"14902"},{"id":"39831","name":"Merkez Yayla Mah (Muratfakilar Köyü)","pk":"14902"},{"id":"39832","name":"Matirlar Yaylasi Mah (Çoğullu Köyü)","pk":"14902"},{"id":"39833","name":"Karşi Yayla Mah (Çoğullu Köyü)","pk":"14902"},{"id":"39834","name":"Kincallar Mah (Koçumlar Köyü)","pk":"14902"},{"id":"39835","name":"Merkez Yaylasi Mah (Kalaç Köyü)","pk":"14902"},{"id":"39836","name":"Merkez Mah (Yenecik Köyü)","pk":"14902"},{"id":"39837","name":"Merkez Mah (Ağizörengüney Köyü)","pk":"14902"},{"id":"39838","name":"Dere Mah (Karacadağdemirciler Köyü)","pk":"14902"},{"id":"39839","name":"Yukari Mah (Halaçlar Köyü)","pk":"14902"},{"id":"39840","name":"Merkez Mah (Hasanlar Köyü)","pk":"14902"},{"id":"39841","name":"Merkez Mah (Karapazar Köyü)","pk":"14902"},{"id":"39842","name":"Merkez Mah (Ümitköy Köyü)","pk":"14902"},{"id":"39843","name":"Merkez Mah (Yakaboy Köyü)","pk":"14902"},{"id":"39844","name":"Merkez Mah (Sipahiler Köyü)","pk":"14902"},{"id":"39845","name":"Yayla Mah (Salur Köyü)","pk":"14902"},{"id":"39846","name":"Yayla Mah (Aşağiörenbaşi Köyü)","pk":"14902"},{"id":"39847","name":"Biçakcilar Mah (Güneydemirciler Köyü)","pk":"14902"},{"id":"39848","name":"Merkez Yaylasi Mah (Koçumlar Köyü)","pk":"14902"},{"id":"39849","name":"Çengeller Yayla Mah (Muratfakilar Köyü)","pk":"14902"},{"id":"39850","name":"Yayla Mah (Kayikiraz Köyü)","pk":"14902"},{"id":"39851","name":"Merkez Yayla Mah (Karacadağdemirciler Köyü)","pk":"14902"},{"id":"39852","name":"Dereköy Mah (Karacadağ Köyü)","pk":"14902"},{"id":"39853","name":"Işikli Yaylasi Mah (Ulaşlar Köyü)","pk":"14902"},{"id":"39854","name":"Yaman Yaylasi Mah (Çalaman Köyü)","pk":"14902"},{"id":"39855","name":"Evrenler Mah (Yakakaya Köyü)","pk":"14902"},{"id":"39856","name":"Toklar Yaylasi Mah (Süllertoklar Köyü)","pk":"14902"},{"id":"39857","name":"Dursunlar Mah (Yakakaya Köyü)","pk":"14902"},{"id":"39858","name":"İmanlar Mah (Bahçedere Köyü)","pk":"14902"},{"id":"39859","name":"Merkez Mah (Yunuslar Köyü)","pk":"14902"},{"id":"39860","name":"Merkez Mah (Koçumlar Köyü)","pk":"14902"},{"id":"39861","name":"Yanşaba Mah (Dağkara Köyü)","pk":"14902"},{"id":"39862","name":"Yayla Mah (Balcilar Köyü)","pk":"14902"},{"id":"39863","name":"Merkez Mah (Yaziköy Köyü)","pk":"14902"},{"id":"39864","name":"Merkez Mah (Geçitler Köyü)","pk":"14902"},{"id":"39865","name":"Aşaği Mah (Nuhören Köyü)","pk":"14902"},{"id":"39866","name":"Merkez Mah (Çoğullu Köyü)","pk":"14902"},{"id":"39867","name":"Merkez Mah (Örencik Köyü)","pk":"14902"},{"id":"39868","name":"Yayla Mah (Aktaşkurtlar Köyü)","pk":"14902"},{"id":"39869","name":"Tekfur Mah (Ertuğrulköy Köyü)","pk":"14902"},{"id":"39870","name":"Gözümler Mah (Demircisopran Köyü)","pk":"14902"},{"id":"39871","name":"Bozuklar Mah (Davutbeyli Köyü)","pk":"14902"},{"id":"39872","name":"Merkez Mah (Kazanlar Köyü)","pk":"14902"},{"id":"39873","name":"Yayla Mah (Nuhören Köyü)","pk":"14902"},{"id":"39874","name":"Yayla Mah (Bünüş Köyü)","pk":"14902"},{"id":"39875","name":"Merkez Yayla Mah (Kösreli Köyü)","pk":"14902"},{"id":"39876","name":"Şükürler Mah (Demircisopran Köyü)","pk":"14902"},{"id":"39877","name":"Siyamlar Mah (Ibricak Köyü)","pk":"14902"},{"id":"39878","name":"Kurtlar Mah (Zeyneller Köyü)","pk":"14902"},{"id":"39879","name":"Merkez Mah (Davutbeyli Köyü)","pk":"14902"},{"id":"39880","name":"Yayla Mah (Eymür Köyü)","pk":"14902"},{"id":"39881","name":"Yayla Mah (Ümitköy Köyü)","pk":"14902"},{"id":"39882","name":"Teççebel Yaylasi Mah (Karapazar Köyü)","pk":"14902"},{"id":"39883","name":"Kurtça Mah (Yağdaş Köyü)","pk":"14902"},{"id":"39884","name":"Biçakcilar Yayla Mah (Güneydemirciler Köyü)","pk":"14902"},{"id":"39885","name":"Merkez Mah (Muratfakilar Köyü)","pk":"14902"},{"id":"39886","name":"Yayla Mah (Ertuğrulköy Köyü)","pk":"14902"},{"id":"39887","name":"Yayla Mah (Çukurca Köyü)","pk":"14902"},{"id":"39888","name":"Katircioğlu Mah (Akçabey Köyü)","pk":"14902"},{"id":"39889","name":"İmamlar Mah (Karacadağdemirciler Köyü)","pk":"14902"},{"id":"39890","name":"Yayla Mah (Mangallar Köyü)","pk":"14902"},{"id":"39891","name":"Merkez Mah (Aşağiovacik Köyü)","pk":"14902"},{"id":"39892","name":"Merkez Mah (Dağkara Köyü)","pk":"14902"},{"id":"39893","name":"Bozkuş Mah (Aktaşkurtlar Köyü)","pk":"14902"},{"id":"39894","name":"Merkez Mah (Asmaca Köyü)","pk":"14902"},{"id":"39895","name":"Yayla Mah (Çayören Köyü)","pk":"14902"},{"id":"39896","name":"Yayla Mah (Hacilar Köyü)","pk":"14902"},{"id":"39897","name":"Sinanlar Mah (Ortaca Köyü)","pk":"14902"},{"id":"39898","name":"Sömerciler Yayla Mah (Karacadağdemirciler Köyü)","pk":"14902"},{"id":"39899","name":"Yayla Mah (Yelkenler Köyü)","pk":"14902"},{"id":"39900","name":"Süller Mah (Süllertoklar Köyü)","pk":"14902"},{"id":"39901","name":"Yayla Mah (Akçaşehir Köyü)","pk":"14902"},{"id":"39902","name":"Yayla Mah (Çalişlar Köyü)","pk":"14902"},{"id":"39903","name":"Yayla Mah (Dursunfaki Köyü)","pk":"14902"},{"id":"39904","name":"Mandiralar Mah (Samat Köyü)","pk":"14902"},{"id":"39905","name":"Merkez Mah (Aydinlar Köyü)","pk":"14902"},{"id":"39906","name":"Merkez Mah (Yazikara Köyü)","pk":"14902"},{"id":"39907","name":"Şahallar Mah (Çoğullu Köyü)","pk":"14902"},{"id":"39908","name":"Merkez Mah (İkinciafşar Köyü)","pk":"14902"},{"id":"39909","name":"Çongallar Mah (Macarlar Köyü)","pk":"14902"},{"id":"39910","name":"Kincallar Yaylasi Mah (Koçumlar Köyü)","pk":"14902"},{"id":"39911","name":"Koçlar Yaylasi Mah (Tatlar Köyü)","pk":"14902"},{"id":"39912","name":"Merkez Mah (Salur Köyü)","pk":"14902"},{"id":"39913","name":"Merkez Mah (Akçaşehir Köyü)","pk":"14902"},{"id":"39914","name":"Çağiş Yaylasi Mah (Çağiş Köyü)","pk":"14902"},{"id":"39915","name":"Merkez Mah (Dikmen Köyü)","pk":"14902"},{"id":"39916","name":"Dere  Mah (Merkez Mah) (Çayörengüney Köyü)","pk":"14902"},{"id":"39917","name":"Eminağa Mah (Beşkonak Köyü)","pk":"14902"},{"id":"39918","name":"Akçagil Mah (Çağiş Köyü)","pk":"14902"},{"id":"39919","name":"Yayla Mah (Yenecik Köyü)","pk":"14902"},{"id":"39920","name":"Merkez Mah (Balcilar Köyü)","pk":"14902"},{"id":"39921","name":"Karşi Mah (Beşkonak Köyü)","pk":"14902"},{"id":"39922","name":"Merkez Mah (Mürdükler Köyü)","pk":"14902"},{"id":"39923","name":"Mehmet Beylik Yaylasi Mah (Havullu Köyü)","pk":"14902"},{"id":"39924","name":"Çobanlar Mah (Göynükören Köyü)","pk":"14902"},{"id":"39925","name":"Merkez Mah (Nuhören Köyü)","pk":"14902"},{"id":"39926","name":"Merkez Mah (Sapanliurgancilar Köyü)","pk":"14902"},{"id":"39927","name":"Çalca Mah (Asmaca Köyü)","pk":"14902"},{"id":"39928","name":"Merkez Mah (Ibricak Köyü)","pk":"14902"},{"id":"39929","name":"Doğancilar Mah (Akçabey Köyü)","pk":"14902"},{"id":"39930","name":"Yayla Mah (Samat Köyü)","pk":"14902"},{"id":"39931","name":"Merkez Yayla Mah (Tatlar Köyü)","pk":"14902"},{"id":"39932","name":"Güney Mah (Çayörengüney Köyü)","pk":"14902"},{"id":"39933","name":"Orta Mah (Asmaca Köyü)","pk":"14902"},{"id":"39934","name":"Macarlar Mah (Macarlar Köyü)","pk":"14902"},{"id":"39935","name":"Yayla Mah (Ağizörengüney Köyü)","pk":"14902"},{"id":"39936","name":"Merkez Mah (Yukariörenbaşi Köyü)","pk":"14902"},{"id":"39937","name":"Köseler Mah (Akçabey Köyü)","pk":"14902"},{"id":"39938","name":"Merkez Mah (Çalişlar Köyü)","pk":"14902"},{"id":"39939","name":"Burgucu Mah (Eymür Köyü)","pk":"14902"},{"id":"39940","name":"Dümenler Yayla Mah (Geçitler Köyü)","pk":"14902"},{"id":"39941","name":"Avlasizgil Mah (Karacadağdemirciler Köyü)","pk":"14902"},{"id":"39942","name":"Avcilar Mah (Yukariörenbaşi Köyü)","pk":"14902"}]}}