{"112":{"name":"Buldan","mah":[{"id":"2581","name":"Yalçinkaya Mah","pk":"20400"},{"id":"2582","name":"Yeşil Dere Mah","pk":"20400"},{"id":"2583","name":"Doğan Mah","pk":"20400"},{"id":"2584","name":"Düzalan Mah","pk":"20400"},{"id":"2585","name":"Helvacilar Mah","pk":"20400"},{"id":"2586","name":"Güroluk Mah","pk":"20400"},{"id":"2587","name":"Girne Mah","pk":"20400"},{"id":"2588","name":"Çatak Mah","pk":"20400"},{"id":"2589","name":"Bostanyeri Mah","pk":"20400"},{"id":"2590","name":"Kaşikci Mah","pk":"20400"},{"id":"2591","name":"Gülalan Mah","pk":"20400"},{"id":"2592","name":"Yeniçam Mah","pk":"20400"},{"id":"2593","name":"Kirandami Mah","pk":"20400"},{"id":"2594","name":"Türlübey Mah","pk":"20400"},{"id":"2595","name":"Çamköy Mah","pk":"20400"},{"id":"2596","name":"Gölbaşi Mah","pk":"20400"},{"id":"2597","name":"Bozalan Mah","pk":"20400"},{"id":"2598","name":"Aktaş Mah","pk":"20400"},{"id":"2599","name":"Beyler Mah","pk":"20400"},{"id":"2600","name":"Dört Eylül Mah","pk":"20400"},{"id":"2601","name":"Yeni Mah","pk":"20400"},{"id":"2602","name":"Yayla Mah","pk":"20400"},{"id":"2603","name":"Hasanbeyler Mah","pk":"20400"},{"id":"2604","name":"Bölmekaya Mah","pk":"20400"},{"id":"2605","name":"Karşiyaka Mah","pk":"20400"},{"id":"2606","name":"Dimbazlar Mah","pk":"20400"},{"id":"2607","name":"Alacaoğlu Mah","pk":"20400"},{"id":"2608","name":"Kovanoluk Mah","pk":"20400"},{"id":"2609","name":"Kurudere Mah","pk":"20400"},{"id":"2610","name":"Boğazçiftlik Mah","pk":"20400"},{"id":"2611","name":"Turan Mah","pk":"20400"},{"id":"2612","name":"Mahmutlu Mah","pk":"20400"},{"id":"2613","name":"Çarşi Mah","pk":"20400"},{"id":"2614","name":"Yenicekent Mah","pk":"20400"},{"id":"2615","name":"Cumhuriyet Mah","pk":"20400"},{"id":"2616","name":"Bursa Mah","pk":"20400"},{"id":"2617","name":"Sarimahmutlu Mah","pk":"20400"},{"id":"2618","name":"Derbent Mah","pk":"20400"},{"id":"2619","name":"Karaköy Mah","pk":"20400"},{"id":"2620","name":"Kadiköy Mah","pk":"20400"},{"id":"2621","name":"Oğuz Mah","pk":"20400"},{"id":"2622","name":"Kurtuluş Mah","pk":"20400"},{"id":"2623","name":"Alandiz Mah","pk":"20400"},{"id":"2624","name":"Süleymanli Mah","pk":"20400"},{"id":"2625","name":"Çaybaşi Mah","pk":"20400"}]}}