{"1749":{"name":"Abana","mah":[{"id":"47077","name":"Merkez Mah","pk":"37970"},{"id":"47078","name":"Bağlik Mah","pk":"37970"},{"id":"47079","name":"Haciveli Mah","pk":"37970"},{"id":"47080","name":"Çayircik Mah","pk":"37970"},{"id":"47081","name":"Konakören Mah","pk":"37970"}]},"1750":{"name":"Merkezköyler","mah":[{"id":"47082","name":"Kirenpinari Mah (Denizbükü Köyü)","pk":"37972"},{"id":"47083","name":"Karahacilar Mah (Çampinar Köyü)","pk":"37972"},{"id":"47084","name":"Altikulaç  Mah (Kadi Mah) (Altikulaç Köyü)","pk":"37972"},{"id":"47085","name":"Müsellim Mah (Akçam Köyü)","pk":"37972"},{"id":"47086","name":"Yemeni Mah (Yemeni Köyü)","pk":"37972"},{"id":"47087","name":"Macar Mah (Göynükler Köyü)","pk":"37972"},{"id":"47088","name":"Çölmek Mah (Altikulaç Köyü)","pk":"37972"},{"id":"47089","name":"Recep Mah (Göynükler Köyü)","pk":"37972"},{"id":"47090","name":"Terzi Mah (Göynükler Köyü)","pk":"37972"},{"id":"47091","name":"Ali Onbaşi Mah (Yeşilyuva Köyü)","pk":"37972"},{"id":"47092","name":"Kuzgun Mah (Akçam Köyü)","pk":"37972"},{"id":"47093","name":"Kalafat Mah (Göynükler Köyü)","pk":"37972"},{"id":"47094","name":"Manav Mah (Çampinar Köyü)","pk":"37972"},{"id":"47095","name":"Soltu Mah (Kadiyusuf Köyü)","pk":"37972"},{"id":"47096","name":"Orza Mah (Altikulaç Köyü)","pk":"37972"},{"id":"47097","name":"Akçam Mah (Maca Mah) (Akçam Köyü)","pk":"37972"},{"id":"47098","name":"Hamza Mah (Yemeni Köyü)","pk":"37972"},{"id":"47099","name":"Elmaçukuru Mah (Elmaçukuru Köyü)","pk":"37972"},{"id":"47100","name":"Kayiş Mah (Yemeni Köyü)","pk":"37972"},{"id":"47101","name":"Nadar Mah (Yeşilyuva Köyü)","pk":"37972"},{"id":"47102","name":"Denizbükü Mah (Denizbükü Köyü)","pk":"37972"},{"id":"47103","name":"Kişlacik Mah (Altikulaç Köyü)","pk":"37972"},{"id":"47104","name":"Deles Mah (Yeşilyuva Köyü)","pk":"37972"},{"id":"47105","name":"Kerim Mah (Altikulaç Köyü)","pk":"37972"},{"id":"47106","name":"Badimana Mah (Yakabaşi Köyü)","pk":"37972"},{"id":"47107","name":"Göynükler Mah (Göynükler Köyü)","pk":"37972"},{"id":"47108","name":"Paşa Mah (Altikulaç Köyü)","pk":"37972"},{"id":"47109","name":"Tarakçi Mah (Akçam Köyü)","pk":"37972"},{"id":"47110","name":"Konak Mah (Göynükler Köyü)","pk":"37972"},{"id":"47111","name":"Ali Kahya Mah (Akçam Köyü)","pk":"37972"},{"id":"47112","name":"Gülen Mah (Göynükler Köyü)","pk":"37972"},{"id":"47113","name":"Kartal Mah (Kadiyusuf Köyü)","pk":"37972"},{"id":"47114","name":"Ziyratlik Mah (Elmaçukuru Köyü)","pk":"37972"},{"id":"47115","name":"Kadiyusuf Mah (Kadiyusuf Köyü)","pk":"37972"},{"id":"47116","name":"Aşçi Mah (Elmaçukuru Köyü)","pk":"37972"},{"id":"47117","name":"Yeşilyuva Mah (Yeşilyuva Köyü)","pk":"37972"},{"id":"47118","name":"Olukyani Mah (Yeşilyuva Köyü)","pk":"37972"},{"id":"47119","name":"Mollaahmet Mah (Göynükler Köyü)","pk":"37972"},{"id":"47120","name":"Koç Mah (Yakabaşi Köyü)","pk":"37972"},{"id":"47121","name":"Ziraatlik Mah (Akçam Köyü)","pk":"37972"},{"id":"47122","name":"Kovalak Mah (Çampinar Köyü)","pk":"37972"},{"id":"47123","name":"Çampinar Mah (Çampinar Köyü)","pk":"37972"},{"id":"47124","name":"Kurtlama Mah (Yemeni Köyü)","pk":"37972"},{"id":"47125","name":"Yakabaşi Mah (Yaylas Mah) (Yakabaşi Köyü)","pk":"37972"},{"id":"47126","name":"Tepe Mah (Akçam Köyü)","pk":"37972"}]}}