{"122":{"name":"Saraylar","mah":[{"id":"2927","name":"Saraylar Mah","pk":"20010"},{"id":"2928","name":"Sirakapilar Mah","pk":"20010"},{"id":"2929","name":"Karaman Mah","pk":"20010"},{"id":"2930","name":"Değirmenönü Mah","pk":"20010"},{"id":"2931","name":"Merkez Efendi Mah","pk":"20010"},{"id":"2932","name":"Akkonak Mah","pk":"20010"},{"id":"2933","name":"İlbade Mah","pk":"20010"},{"id":"2934","name":"Altintop Mah","pk":"20010"},{"id":"2935","name":"Muratdede Mah","pk":"20010"}]},"123":{"name":"Üzerlik","mah":[{"id":"2936","name":"Çeltikçi Mah","pk":"20060"},{"id":"2937","name":"Salihağa Mah","pk":"20060"},{"id":"2938","name":"Aşağişamli Mah","pk":"20060"},{"id":"2939","name":"Üzerlik Mah","pk":"20060"}]},"124":{"name":"Üçler","mah":[{"id":"2940","name":"Hacieyüplü Mah","pk":"20050"},{"id":"2941","name":"Hallaçlar Mah","pk":"20050"},{"id":"2942","name":"1200 Evler Mah","pk":"20050"},{"id":"2943","name":"Göveçlik Mah","pk":"20050"},{"id":"2944","name":"Karahasanli Mah","pk":"20050"},{"id":"2945","name":"Barbaros Mah","pk":"20050"},{"id":"2946","name":"Altindere Mah","pk":"20050"},{"id":"2947","name":"Çakmak Mah","pk":"20050"},{"id":"2948","name":"Yeşilyayla Mah","pk":"20050"},{"id":"2949","name":"Saruhan Mah","pk":"20050"},{"id":"2950","name":"Başkarci Mah","pk":"20050"}]},"125":{"name":"Gümüşler","mah":[{"id":"2951","name":"Gümüşçay Mah","pk":"20030"},{"id":"2952","name":"Mehmet Akif Ersoy Mah","pk":"20030"},{"id":"2953","name":"Yenişafak Mah","pk":"20030"},{"id":"2954","name":"Selçuk Bey Mah","pk":"20030"},{"id":"2955","name":"Alpaslan Mah","pk":"20030"},{"id":"2956","name":"Şemikler Mah","pk":"20030"},{"id":"2957","name":"Kayalar Mah","pk":"20030"},{"id":"2958","name":"Gültepe Mah","pk":"20030"},{"id":"2959","name":"Yeni Mah","pk":"20030"}]},"126":{"name":"Sümer","mah":[{"id":"2960","name":"Akçeşme Mah","pk":"20020"},{"id":"2961","name":"Sümer Mah","pk":"20020"},{"id":"2962","name":"Bozburun Mah","pk":"20020"},{"id":"2963","name":"Eskihisar Mah","pk":"20020"},{"id":"2964","name":"Zafer Mah","pk":"20020"},{"id":"2965","name":"Sevindik Mah","pk":"20020"},{"id":"2966","name":"Kumkisik Mah","pk":"20020"}]},"127":{"name":"Adalet","mah":[{"id":"2967","name":"Hisar Mah","pk":"20040"},{"id":"2968","name":"Barutçular Mah","pk":"20040"},{"id":"2969","name":"Kadilar Mah","pk":"20040"},{"id":"2970","name":"Yenişehir Mah","pk":"20040"},{"id":"2971","name":"Şirinköy Mah","pk":"20040"},{"id":"2972","name":"Gerzele Mah","pk":"20040"},{"id":"2973","name":"Adalet Mah","pk":"20040"},{"id":"2974","name":"Servergazi Mah","pk":"20040"},{"id":"2975","name":"Bahçelievler Mah","pk":"20040"},{"id":"2976","name":"Bereketler Mah","pk":"20040"}]}}