{"2143":{"name":"Petrol","mah":[{"id":"57766","name":"Petrol Mah","pk":"72040"},{"id":"57767","name":"Güneykent Mah","pk":"72040"},{"id":"57768","name":"Site Mah","pk":"72040"},{"id":"57769","name":"Petrolkent Mah","pk":"72040"},{"id":"57770","name":"Karşiyaka Mah","pk":"72040"},{"id":"57771","name":"Seyitler Mah","pk":"72040"},{"id":"57772","name":"Akyürek Mah","pk":"72040"},{"id":"57773","name":"Erköklü Mah (Erköklü Köyü)","pk":"72040"},{"id":"57774","name":"Hürriyet Mah","pk":"72040"},{"id":"57775","name":"Çamlica Mah","pk":"72040"}]},"2144":{"name":"Çarşi","mah":[{"id":"57776","name":"Beşevler Mah","pk":"72050"},{"id":"57777","name":"Kismet Mah","pk":"72050"},{"id":"57778","name":"Yeşiltepe Mah","pk":"72050"},{"id":"57779","name":"İluh Mah","pk":"72050"},{"id":"57780","name":"Çay Mah","pk":"72050"},{"id":"57781","name":"Huzur Mah","pk":"72050"},{"id":"57782","name":"Yeni Mah","pk":"72050"},{"id":"57783","name":"19 Mayis Mah","pk":"72050"},{"id":"57784","name":"Çarşi Mah","pk":"72050"},{"id":"57785","name":"Meydan Mah","pk":"72050"},{"id":"57786","name":"Aydinlikevler Mah","pk":"72050"}]},"2145":{"name":"Gap","mah":[{"id":"57787","name":"Şafak Mah","pk":"72070"},{"id":"57788","name":"Bayindir Mah","pk":"72070"},{"id":"57789","name":"Fatih Mah","pk":"72070"},{"id":"57790","name":"Belde Mah","pk":"72070"},{"id":"57791","name":"Çamlitepe Mah","pk":"72070"},{"id":"57792","name":"Gap Mah","pk":"72070"},{"id":"57793","name":"Tilmerc Mah","pk":"72070"},{"id":"57794","name":"Şirinevler Mah","pk":"72070"},{"id":"57795","name":"Gültepe Mah","pk":"72070"},{"id":"57796","name":"Korik Mah","pk":"72070"},{"id":"57797","name":"Cumhuriyet Mah","pk":"72070"},{"id":"57798","name":"Cudi Mah","pk":"72070"},{"id":"57799","name":"Bahçelievler Mah","pk":"72070"}]},"2146":{"name":"Kültür","mah":[{"id":"57800","name":"Hilal Mah","pk":"72060"},{"id":"57801","name":"Raman Mah","pk":"72060"},{"id":"57802","name":"Bağlar Mah","pk":"72060"},{"id":"57803","name":"Kültür Mah","pk":"72060"},{"id":"57804","name":"Sağlik Mah","pk":"72060"},{"id":"57805","name":"Pinarbaşi Mah","pk":"72060"},{"id":"57806","name":"Ziyagökalp Mah","pk":"72060"},{"id":"57807","name":"Pazaryeri Mah","pk":"72060"}]},"2147":{"name":"Merkezköyler","mah":[{"id":"57808","name":"Oymataş Köyü","pk":"72100"},{"id":"57809","name":"Ünlüce Mah (Oymataş Köyü)","pk":"72100"},{"id":"57810","name":"Salkimli Mah (Çayüstü Köyü)","pk":"72100"},{"id":"57811","name":"Kiliç Köyü","pk":"72100"},{"id":"57812","name":"Hanli Mah (Binatli Köyü)","pk":"72100"},{"id":"57813","name":"Şeyhçoban Mah (Oymataş Köyü)","pk":"72100"},{"id":"57814","name":"Okçu Mah (Karayün Köyü)","pk":"72100"},{"id":"57815","name":"Akça Köyü","pk":"72100"},{"id":"57816","name":"Doluca Köyü","pk":"72100"},{"id":"57817","name":"Biçakçi Köyü","pk":"72100"},{"id":"57818","name":"Seyrantepe Mah (Balpinar Köyü)","pk":"72100"},{"id":"57819","name":"Yeniköy Köyü","pk":"72100"},{"id":"57820","name":"Yeşilöz Köyü","pk":"72100"},{"id":"57821","name":"Yoğurtlu Mah (Bayrakli Köyü)","pk":"72100"},{"id":"57822","name":"Segirkan Köyü","pk":"72100"},{"id":"57823","name":"Suçeken Köyü","pk":"72100"},{"id":"57824","name":"Demirbilek Köyü","pk":"72100"},{"id":"57825","name":"Aziziye Mah (Yaylica Köyü)","pk":"72100"},{"id":"57826","name":"Esentepe Mah (Doluca Köyü)","pk":"72100"},{"id":"57827","name":"Best Mah (Binatli Köyü)","pk":"72100"},{"id":"57828","name":"Akoba Köyü","pk":"72100"},{"id":"57829","name":"Diktepe Köyü","pk":"72100"},{"id":"57830","name":"Çayüstü Köyü","pk":"72100"},{"id":"57831","name":"Demirlipinar Köyü","pk":"72100"},{"id":"57832","name":"Uğrak Mah (Yağmurlu Köyü)","pk":"72100"},{"id":"57833","name":"Haci Ömer Mah (Çayüstü Köyü)","pk":"72100"},{"id":"57834","name":"Reyhan Mah (Güneşli Köyü)","pk":"72100"},{"id":"57835","name":"Yakitli Köyü","pk":"72100"},{"id":"57836","name":"Sincanli Mah (Oymataş Köyü)","pk":"72100"},{"id":"57837","name":"Çarikli Köyü","pk":"72100"},{"id":"57838","name":"Recepler Köyü","pk":"72100"},{"id":"57839","name":"Yağmurlu Köyü","pk":"72100"},{"id":"57840","name":"Yolağzi Köyü","pk":"72100"},{"id":"57841","name":"Ödemiş Mah (Çarikli Köyü)","pk":"72100"},{"id":"57842","name":"Belikli Mah (Güneşli Köyü)","pk":"72100"},{"id":"57843","name":"Karayün Köyü","pk":"72100"},{"id":"57844","name":"Çeşmebaşi Mah (Demirbilek Köyü)","pk":"72100"},{"id":"57845","name":"Yeni Köy Mah (Diktepe Köyü)","pk":"72100"},{"id":"57846","name":"Badelen Mah (Kayabaği Köyü)","pk":"72100"},{"id":"57847","name":"Yediyol Köyü","pk":"72100"},{"id":"57848","name":"Kayabaği Köyü","pk":"72100"},{"id":"57849","name":"Yenişehir Mah","pk":"72100"},{"id":"57850","name":"Kirmataş Mah (Kayabaği Köyü)","pk":"72100"},{"id":"57851","name":"Kolbaşi Mah (Binatli Köyü)","pk":"72100"},{"id":"57852","name":"Urganli Köyü","pk":"72100"},{"id":"57853","name":"Bayrakli Köyü","pk":"72100"},{"id":"57854","name":"Oluklu Mah (Yaylica Köyü)","pk":"72100"},{"id":"57855","name":"Yaylica Köyü","pk":"72100"},{"id":"57856","name":"Güneşli Köyü","pk":"72100"},{"id":"57857","name":"Güvercin Köyü","pk":"72100"},{"id":"57858","name":"Kösetarla Köyü","pk":"72100"},{"id":"57859","name":"Yenimahalle Mah (Balpinar Köyü)","pk":"72100"},{"id":"57860","name":"Çayeli Mah (Demirlipinar Köyü)","pk":"72100"},{"id":"57861","name":"Gölbaşi Mah (Diktepe Köyü)","pk":"72100"},{"id":"57862","name":"Zorköy Mah (Yeniköy Köyü)","pk":"72100"},{"id":"57863","name":"Selamet Mah (Bayrakli Köyü)","pk":"72100"},{"id":"57864","name":"Soğuksu Mah (Oymataş Köyü)","pk":"72100"},{"id":"57865","name":"Kocalar Köyü","pk":"72100"},{"id":"57866","name":"Binatli Köyü","pk":"72100"},{"id":"57867","name":"Kumtepe Mah (Kösetarla Köyü)","pk":"72100"},{"id":"57868","name":"Demirci Mah (Akoba Köyü)","pk":"72100"},{"id":"57869","name":"Şerbet Mah (Yaylica Köyü)","pk":"72100"},{"id":"57870","name":"Üçtepe Mah (Güneşli Köyü)","pk":"72100"},{"id":"57871","name":"Kesmeköprü Köyü","pk":"72100"},{"id":"57872","name":"İkiztepe Mah (İkiztepe Köyü)","pk":"72100"},{"id":"57873","name":"Yolveren Köyü","pk":"72100"},{"id":"57874","name":"Kuyubaşi Köyü","pk":"72100"},{"id":"57875","name":"Neval Mah (Güneşli Köyü)","pk":"72100"}]}}