{"2166":{"name":"Yakakent","mah":[{"id":"58806","name":"Liman Mah","pk":"55810"},{"id":"58807","name":"Büyükkirik Mah","pk":"55810"},{"id":"58808","name":"Çamalan Mah","pk":"55810"},{"id":"58809","name":"Kayali Mah","pk":"55810"},{"id":"58810","name":"Kuzören Mah","pk":"55810"},{"id":"58811","name":"Sarigöl Mah","pk":"55810"},{"id":"58812","name":"Merkez Mah","pk":"55810"},{"id":"58813","name":"Çepni Mah","pk":"55810"},{"id":"58814","name":"Yeşilköy Mah","pk":"55810"},{"id":"58815","name":"Küplüağzi Mah","pk":"55810"},{"id":"58816","name":"Gündüzlü Mah","pk":"55810"},{"id":"58817","name":"Asmapinar Mah","pk":"55810"},{"id":"58818","name":"Yassidağ Mah","pk":"55810"},{"id":"58819","name":"Kozköy Mah","pk":"55810"},{"id":"58820","name":"Kürüz Mah","pk":"55810"},{"id":"58821","name":"Mutafli Mah","pk":"55810"},{"id":"58822","name":"Karaaba Mah","pk":"55810"}]}}